Metadata-Version: 2.4
Name: peak-locator
Version: 1.1.2
Summary: A robust Python toolkit for deterministic peak detection in one-dimensional, two-dimensional, and higher-dimensional numerical data
Author-email: Chiraag Kakar <chiraag.kakar.22@gmail.com>
License: MIT
Project-URL: Homepage, https://github.com/chiraag-kakar/peak-locator
Project-URL: Documentation, https://chiraag-kakar.github.io/peak-locator/
Project-URL: Repository, https://github.com/chiraag-kakar/peak-locator
Project-URL: Issues, https://github.com/chiraag-kakar/peak-locator/issues
Project-URL: Changelog, https://github.com/chiraag-kakar/peak-locator/blob/main/CHANGELOG.md
Keywords: peak-detection,signal-processing,data-analysis,algorithms,numpy,scipy
Classifier: Development Status :: 3 - Alpha
Classifier: Intended Audience :: Developers
Classifier: Intended Audience :: Science/Research
Classifier: License :: OSI Approved :: MIT License
Classifier: Operating System :: OS Independent
Classifier: Programming Language :: Python :: 3
Classifier: Programming Language :: Python :: 3.9
Classifier: Programming Language :: Python :: 3.10
Classifier: Programming Language :: Python :: 3.11
Classifier: Programming Language :: Python :: 3.12
Classifier: Topic :: Scientific/Engineering
Classifier: Topic :: Scientific/Engineering :: Mathematics
Classifier: Topic :: Software Development :: Libraries :: Python Modules
Classifier: Typing :: Typed
Requires-Python: >=3.9
License-File: LICENSE
Requires-Dist: numpy>=1.21.0
Provides-Extra: dev
Requires-Dist: pytest>=7.0.0; extra == "dev"
Requires-Dist: pytest-cov>=4.0.0; extra == "dev"
Requires-Dist: black>=23.0.0; extra == "dev"
Requires-Dist: ruff>=0.1.0; extra == "dev"
Requires-Dist: mypy>=1.0.0; extra == "dev"
Provides-Extra: viz
Requires-Dist: matplotlib>=3.5.0; extra == "viz"
Dynamic: license-file
